mexpress-0.1.8.dist-info/METADATA
mexpress-0.1.8.dist-info/WHEEL
mexpress-0.1.8.dist-info/licenses/LICENSE
mexpress/__init__.py
mexpress/_mexpress.cpython-313-i386-linux-gnu.so
mexpress-0.1.8.dist-info/RECORD
