Metadata-Version: 2.4
Name: mexpress
Version: 0.1.8
Requires-Dist: numpy
License-File: LICENSE
Summary: Math parser and evaluator capable of computing gradients and Hessians.
Requires-Python: >=3.10
